a_pandas_ex_adb_execute_activities/LICENSE
a_pandas_ex_adb_execute_activities/README.MD
a_pandas_ex_adb_execute_activities/__init__.py
a_pandas_ex_adb_execute_activities/requirements.txt
a_pandas_ex_adb_execute_activities/thirdparty.json
a_pandas_ex_adb_execute_activities-0.10.dist-info/LICENSE.rst
a_pandas_ex_adb_execute_activities-0.10.dist-info/METADATA
a_pandas_ex_adb_execute_activities-0.10.dist-info/WHEEL
a_pandas_ex_adb_execute_activities-0.10.dist-info/top_level.txt
a_pandas_ex_adb_execute_activities-0.10.dist-info/RECORD
