Metadata-Version: 2.1
Name: a_pandas_ex_adb_execute_activities
Version: 0.10
Summary: Creates (partial) functions for every Android activity using ADB 
Home-page: https://github.com/hansalemaos/a_pandas_ex_adb_execute_activities
Author: Johannes Fischer
Author-email: <aulasparticularesdealemaosp@gmail.com>
License: MIT
Keywords: activity,uiautomator,dumpsys,adb,android,debugging,pandas,DataFrame,automation
Classifier: Development Status :: 4 - Beta
Classifier: Programming Language :: Python :: 3 :: Only
Classifier: Programming Language :: Python :: 3.9
Classifier: Topic :: Scientific/Engineering :: Visualization
Classifier: Topic :: Software Development :: Libraries :: Python Modules
Classifier: Topic :: Text Editors :: Text Processing
Classifier: Topic :: Text Processing :: General
Classifier: Topic :: Text Processing :: Indexing
Classifier: Topic :: Text Processing :: Filters
Classifier: Topic :: Utilities
License-File: LICENSE.rst
